	[ {"label":"All", "data":1},
		{"label":"Action", "data":2},
		{"label":"Audio", "data":3},
		{"label":"Button", "data":4},
		{"label":"Canvas", "data":5},
		{"label":"Countdown", "data":6},
		{"label":"Drag", "data":7},
		{"label":"Dynamic Text", "data":8},
		{"label":"External Code", "data":9},
		{"label":"Filter", "data":10},
		{"label":"Group", "data":11},
		{"label":"Hide", "data":12},
		{"label":"Linear Animation", "data":13},
		{"label":"Mask", "data":14},
		{"label":"Map", "data":15},
		{"label":"Multiplier", "data":16},
		{"label":"Path Animation", "data":17},
		{"label":"Physics Body", "data":18},
		{"label":"Physics Collisions", "data":19},
		{"label":"Physics Force", "data":20},
		{"label":"Physics Joints", "data":21},
		{"label":"Pinch", "data":22},
		{"label":"Scroll", "data":23},
		{"label":"Set Language", "data":24},
		{"label":"Shake", "data":25},
		{"label":"Spin", "data":26},
		{"label":"Sprite Sheet", "data":27},
		{"label":"Swipe", "data":28},
		{"label":"Switch Images", "data":29},
		{"label":"Sync Text", "data":30},
		{"label":"Text", "data":31},
		{"label":"Text Input", "data":32},
		{"label":"Timer", "data":33},
		{"label":"Variable", "data":34},
		{"label":"Vector", "data":35},
		{"label":"Video", "data":36},
		{"label":"Web", "data":37},
		{"label":"Widget Blink", "data":38},
		{"label":"Widget Bounce", "data":39},
		{"label":"Widget Pulse", "data":40},
		{"label":"Widget Rotation", "data":41},
		{"label":"Widget Shake", "data":42},
		{"label":"Parallax", "data":43},
		{"label":"Particles", "data":44}
]